dagviz.py
py_dagviz-0.1.0.dist-info/LICENSE
py_dagviz-0.1.0.dist-info/METADATA
py_dagviz-0.1.0.dist-info/WHEEL
py_dagviz-0.1.0.dist-info/top_level.txt
py_dagviz-0.1.0.dist-info/RECORD
