Metadata-Version: 2.1
Name: py-dagviz
Version: 0.1.0
Summary: CLI visualizer of directed acyclic graphs
Author-email: Tongfei Chen <tongfei@pm.me>
License: MIT License        
Project-URL: Homepage, https://github.com/ctongfei/py-dagviz
Project-URL: Bug Tracker, https://github.com/ctongfei/py-dagviz/issues
Requires-Python: >=3.7
License-File: LICENSE
Requires-Dist: networkx (>=2.8)
